odoo/addons/ssi_stock_account/README.rst
odoo/addons/ssi_stock_account/__init__.py
odoo/addons/ssi_stock_account/__manifest__.py
odoo/addons/ssi_stock_account/i18n/ssi_stock_account.pot
odoo/addons/ssi_stock_account/models/__init__.py
odoo/addons/ssi_stock_account/models/account_move_line.py
odoo/addons/ssi_stock_account/models/picking_type_category.py
odoo/addons/ssi_stock_account/models/stock_location.py
odoo/addons/ssi_stock_account/models/stock_move.py
odoo/addons/ssi_stock_account/models/stock_picking.py
odoo/addons/ssi_stock_account/models/stock_picking_type.py
odoo/addons/ssi_stock_account/models/stock_valuation_layer.py
odoo/addons/ssi_stock_account/models/stock_valuation_layer_usage.py
odoo/addons/ssi_stock_account/security/ir.model.access.csv
odoo/addons/ssi_stock_account/static/description/icon.png
odoo/addons/ssi_stock_account/views/stock_move_views.xml
odoo/addons/ssi_stock_account/views/stock_picking_type_views.xml
odoo/addons/ssi_stock_account/views/stock_picking_views.xml
odoo/addons/ssi_stock_account/views/stock_valuation_layer_views.xml
odoo/addons/ssi_stock_account/wizards/__init__.py
odoo/addons/ssi_stock_account/wizards/change_picking_actual_movement_date.py
odoo/addons/ssi_stock_account/wizards/recompute_stock_valuation_layer_usage.py
odoo/addons/ssi_stock_account/wizards/recompute_stock_valuation_layer_usage_views.xml
odoo14_addon_ssi_stock_account-14.0.2.26.1.dist-info/METADATA
odoo14_addon_ssi_stock_account-14.0.2.26.1.dist-info/WHEEL
odoo14_addon_ssi_stock_account-14.0.2.26.1.dist-info/top_level.txt
odoo14_addon_ssi_stock_account-14.0.2.26.1.dist-info/RECORD
